LICENCE
README.md
setup.py
game_utilities_py/__init__.py
game_utilities_py/controle_sistema.py
game_utilities_py/uteis.py
game_utilities_py.egg-info/PKG-INFO
game_utilities_py.egg-info/SOURCES.txt
game_utilities_py.egg-info/dependency_links.txt
game_utilities_py.egg-info/requires.txt
game_utilities_py.egg-info/top_level.txt