Metadata-Version: 2.1
Name: game-utilities-py
Version: 1.0.0
Summary: Game Utilities
Author: George Júnior
Author-email: ctt.georgejr@gmail.com
License: MIT License
Keywords: game utilities
License-File: LICENCE
Requires-Dist: opencv-python
Requires-Dist: requests
Requires-Dist: numpy
Requires-Dist: PyAutoGUI
Requires-Dist: keyboard
Requires-Dist: colorama
